monoco/main.py
monoco/cli/__init__.py
monoco/cli/project.py
monoco/cli/workspace.py
monoco/core/__init__.py
monoco/core/config.py
monoco/core/execution.py
monoco/core/feature.py
monoco/core/git.py
monoco/core/githooks.py
monoco/core/injection.py
monoco/core/integrations.py
monoco/core/lsp.py
monoco/core/output.py
monoco/core/registry.py
monoco/core/setup.py
monoco/core/skill_framework.py
monoco/core/skills.py
monoco/core/state.py
monoco/core/sync.py
monoco/core/telemetry.py
monoco/core/workflow_converter.py
monoco/core/workspace.py
monoco/core/hooks/__init__.py
monoco/core/hooks/base.py
monoco/core/hooks/context.py
monoco/core/hooks/registry.py
monoco/core/hooks/builtin/__init__.py
monoco/core/hooks/builtin/git_cleanup.py
monoco/core/hooks/builtin/logging_hook.py
monoco/core/resource/__init__.py
monoco/core/resource/finder.py
monoco/core/resource/manager.py
monoco/core/resource/models.py
monoco/core/resources/en/AGENTS.md
monoco/core/resources/en/skills/monoco_core/SKILL.md
monoco/core/resources/zh/AGENTS.md
monoco/core/resources/zh/skills/monoco_core/SKILL.md
monoco/daemon/__init__.py
monoco/daemon/app.py
monoco/daemon/commands.py
monoco/daemon/models.py
monoco/daemon/reproduce_stats.py
monoco/daemon/services.py
monoco/daemon/stats.py
monoco/features/__init__.py
monoco/features/agent/__init__.py
monoco/features/agent/adapter.py
monoco/features/agent/apoptosis.py
monoco/features/agent/cli.py
monoco/features/agent/config.py
monoco/features/agent/defaults.py
monoco/features/agent/engines.py
monoco/features/agent/flow_skills.py
monoco/features/agent/manager.py
monoco/features/agent/models.py
monoco/features/agent/session.py
monoco/features/agent/worker.py
monoco/features/agent/resources/atoms/atom-code-dev.yaml
monoco/features/agent/resources/atoms/atom-issue-lifecycle.yaml
monoco/features/agent/resources/atoms/atom-knowledge.yaml
monoco/features/agent/resources/atoms/atom-review.yaml
monoco/features/agent/resources/en/skills/flow_engineer/SKILL.md
monoco_toolkit-0.3.10.dist-info/METADATA
monoco_toolkit-0.3.10.dist-info/WHEEL
monoco_toolkit-0.3.10.dist-info/entry_points.txt
monoco_toolkit-0.3.10.dist-info/licenses/LICENSE
monoco_toolkit-0.3.10.dist-info/RECORD
