Metadata-Version: 2.4
Name: monoco-toolkit
Version: 0.3.10
Summary: Agent Native Toolkit for Monoco - Task Management & Kanban for AI Agents
Project-URL: Homepage, https://monoco.io
Project-URL: Repository, https://github.com/IndenScale/Monoco
Project-URL: Documentation, https://monoco.io/docs
Project-URL: Issues, https://github.com/IndenScale/Monoco/issues
Author-email: Monoco Team <dev@monoco.io>
License-Expression: MIT
License-File: LICENSE
Keywords: agent-native,ai-agents,cli,kanban,monoco,task-management,workflow
Classifier: Development Status :: 3 - Alpha
Classifier: Intended Audience :: Developers
Classifier: License :: OSI Approved :: MIT License
Classifier: Programming Language :: Python :: 3
Classifier: Programming Language :: Python :: 3.10
Classifier: Programming Language :: Python :: 3.11
Classifier: Programming Language :: Python :: 3.12
Classifier: Topic :: Office/Business :: Groupware
Classifier: Topic :: Software Development :: Libraries :: Python Modules
Classifier: Topic :: Software Development :: Quality Assurance
Requires-Python: >=3.10
Requires-Dist: fastapi>=0.100.0
Requires-Dist: httpx>=0.28.1
Requires-Dist: prompt-toolkit>=3.0.0
Requires-Dist: pydantic>=2.0.0
Requires-Dist: pyyaml>=6.0
Requires-Dist: rich>=13.0.0
Requires-Dist: sse-starlette>=1.6.0
Requires-Dist: typer[all]>=0.9.0
Requires-Dist: uvicorn[standard]>=0.20.0
Requires-Dist: watchdog>=6.0.0
